social_tools/__init__.py
social_tools/emotion_detection.py
social_tools/sentiment_analysis.py
social_tools/toxicity_detection.py
social_tools/utils.py
social_tools-1.0.2.dev0.dist-info/LICENSE
social_tools-1.0.2.dev0.dist-info/METADATA
social_tools-1.0.2.dev0.dist-info/WHEEL
social_tools-1.0.2.dev0.dist-info/top_level.txt
social_tools-1.0.2.dev0.dist-info/RECORD
