Metadata-Version: 2.1
Name: social_tools
Version: 1.0.2.dev0
Summary: The goal is to provide a unified interface to interact with various social analysis tools
Home-page: https://github.com/instabaines/social_tools_lib/
Download-URL: https://github.com/instabaines/social_tools_lib/archive/refs/tags/1.0.1dev.tar.gz
Author: Ridwan Amure
Author-email: amureridwan002@gmail.com
License: MIT
Keywords: social tools,sentiment analysis,toxicity,emotion analysis
Classifier: Development Status :: 3 - Alpha
Classifier: License :: OSI Approved :: MIT License
Classifier: Programming Language :: Python
Classifier: Programming Language :: Python :: 3
Classifier: Programming Language :: Python :: 3.10
Classifier: Programming Language :: Python :: 3.11
Classifier: Natural Language :: English
Classifier: Operating System :: OS Independent
Requires-Python: >=3.10.0
License-File: LICENSE
Requires-Dist: numpy==1.26.4
Requires-Dist: transformers
Requires-Dist: detoxify
Requires-Dist: pytest>=6.0
Requires-Dist: textblob>=0.15.3
Requires-Dist: spacy>=3.7.4
Requires-Dist: spacytextblob>=4.0.0
Requires-Dist: nltk>=3.8.1
